MANIFEST.in
README.txt
setup.cfg
setup.py
docs/HISTORY.txt
docs/INSTALL.txt
docs/LICENSE.txt
jalon/__init__.py
jalon.primo.egg-info/PKG-INFO
jalon.primo.egg-info/SOURCES.txt
jalon.primo.egg-info/dependency_links.txt
jalon.primo.egg-info/entry_points.txt
jalon.primo.egg-info/namespace_packages.txt
jalon.primo.egg-info/not-zip-safe
jalon.primo.egg-info/paster_plugins.txt
jalon.primo.egg-info/requires.txt
jalon.primo.egg-info/top_level.txt
jalon/primo/__init__.py
jalon/primo/configure.zcml
jalon/primo/exportimport.py
jalon/primo/profiles.zcml
jalon/primo/tests.py
jalon/primo/utility.py
jalon/primo/browser/__init__.py
jalon/primo/browser/browser.py
jalon/primo/browser/configure.zcml
jalon/primo/browser/controlpanel.py
jalon/primo/browser/images/primo_icon.gif
jalon/primo/browser/interfaces/__init__.py
jalon/primo/browser/interfaces/browser.py
jalon/primo/browser/interfaces/controlpanel.py
jalon/primo/interfaces/__init__.py
jalon/primo/interfaces/utility.py
jalon/primo/profiles/default/actionicons.xml
jalon/primo/profiles/default/componentregistry.xml
jalon/primo/profiles/default/controlpanel.xml
jalon/primo/profiles/default/metadata.xml
jalon/primo/profiles/default/portal-primo.txt
jalon/primo/profiles/default/primo.xml
jalon/primo/profiles/default/toolset.xml