Metadata-Version: 1.1
Name: jalon.primo
Version: 1.2
Summary: Primo connecteur
Home-page: http://unice.fr
Author: Bordonado Christophe - Université Nice Sophia Antipolis (uns) Service TICE/ Jean Bado - Université Versaille Saint-Quentin(UVSQ)
Author-email: tice@unice.fr
License: GPL
Platform: UNKNOWN
Classifier: Framework :: Plone
Classifier: Programming Language :: Python
